<?xml version="1.0" encoding="UTF-8"?>
<java-wsdl-mapping xmlns="http://java.sun.com/xml/ns/j2ee"
  xmlns:xsi="http://www.w3.org/2001/XMLSchema-instance"
  xsi:schemaLocation="http://java.sun.com/xml/ns/j2ee
  http://www.ibm.com/webservices/xsd/j2ee_jaxrpc_mapping_1_1.xsd"
  version="1.1">

    <package-mapping>
        <package-type>com.reuters.ns._2007._09._01.gcap.eai.cs.fixedlengthrequest</package-type>
        <namespaceURI>http://www.reuters.com/ns/2007/09/01/GCAP/EAI/CS/FixedLengthRequest</namespaceURI>
    </package-mapping>
    <package-mapping>
        <package-type>com.reuters.ns._2007._09._01.gcap.eai.cs.acm.accountcontactpublish</package-type>
        <namespaceURI>http://www.reuters.com/ns/2007/09/01/GCAP/EAI/CS/ACM/AccountContactPublish</namespaceURI>
    </package-mapping>
    <package-mapping>
        <package-type>com.reuters.eai.cs.acm</package-type>
        <namespaceURI>http://www.reuters.com/ns/2007/09/01/GCAP/CS/ACM/AccountContactRequestFormatter</namespaceURI>
    </package-mapping>
    <java-xml-type-mapping>
        <java-type>com.reuters.ns._2007._09._01.gcap.eai.cs.acm.accountcontactpublish._CSContact</java-type>
        <root-type-qname xmlns:typeNS="http://www.reuters.com/ns/2007/09/01/GCAP/EAI/CS/ACM/AccountContactPublish">typeNS:_CSContact</root-type-qname>
        <qname-scope>complexType</qname-scope>
        <variable-mapping>
            <java-variable-name>contactId</java-variable-name>
            <xml-element-name>contactId</xml-element-name>
        </variable-mapping>
        <variable-mapping>
            <java-variable-name>personId</java-variable-name>
            <xml-element-name>personId</xml-element-name>
        </variable-mapping>
        <variable-mapping>
            <java-variable-name>contactType</java-variable-name>
            <xml-element-name>contactType</xml-element-name>
        </variable-mapping>
        <variable-mapping>
            <java-variable-name>responsibilityCode</java-variable-name>
            <xml-element-name>responsibilityCode</xml-element-name>
        </variable-mapping>
        <variable-mapping>
            <java-variable-name>firstName</java-variable-name>
            <xml-element-name>firstName</xml-element-name>
        </variable-mapping>
        <variable-mapping>
            <java-variable-name>lastName</java-variable-name>
            <xml-element-name>lastName</xml-element-name>
        </variable-mapping>
        <variable-mapping>
            <java-variable-name>title</java-variable-name>
            <xml-element-name>title</xml-element-name>
        </variable-mapping>
        <variable-mapping>
            <java-variable-name>jobTitle</java-variable-name>
            <xml-element-name>jobTitle</xml-element-name>
        </variable-mapping>
        <variable-mapping>
            <java-variable-name>businessTelephoneNumber</java-variable-name>
            <xml-element-name>businessTelephoneNumber</xml-element-name>
        </variable-mapping>
        <variable-mapping>
            <java-variable-name>homeTelephoneNumber</java-variable-name>
            <xml-element-name>homeTelephoneNumber</xml-element-name>
        </variable-mapping>
        <variable-mapping>
            <java-variable-name>messageId</java-variable-name>
            <xml-element-name>messageId</xml-element-name>
        </variable-mapping>
    </java-xml-type-mapping>
    <java-xml-type-mapping>
        <java-type>com.reuters.ns._2007._09._01.gcap.eai.cs.fixedlengthrequest._CSBasicResponse</java-type>
        <root-type-qname xmlns:typeNS="http://www.reuters.com/ns/2007/09/01/GCAP/EAI/CS/FixedLengthRequest">typeNS:_CSBasicResponse</root-type-qname>
        <qname-scope>complexType</qname-scope>
        <variable-mapping>
            <java-variable-name>response</java-variable-name>
            <xml-element-name>response</xml-element-name>
        </variable-mapping>
        <variable-mapping>
            <java-variable-name>responseCode</java-variable-name>
            <xml-element-name>responseCode</xml-element-name>
        </variable-mapping>
        <variable-mapping>
            <java-variable-name>responseMessage</java-variable-name>
            <xml-element-name>responseMessage</xml-element-name>
        </variable-mapping>
    </java-xml-type-mapping>
     <java-xml-type-mapping>
        <java-type>com.reuters.ns._2007._09._01.gcap.eai.cs.fixedlengthrequest._CSResponse</java-type>
        <root-type-qname xmlns:typeNS="http://www.reuters.com/ns/2007/09/01/GCAP/EAI/CS/FixedLengthRequest">typeNS:_CSResponse</root-type-qname>
        <qname-scope>simpleType</qname-scope>
        <variable-mapping>
            <java-variable-name>value</java-variable-name>
            <xml-element-name>value</xml-element-name>
        </variable-mapping>        
    </java-xml-type-mapping>
    <java-xml-type-mapping>
        <java-type>com.reuters.ns._2007._09._01.gcap.eai.cs.fixedlengthrequest._CSEaiHeader</java-type>
        <root-type-qname xmlns:typeNS="http://www.reuters.com/ns/2007/09/01/GCAP/EAI/CS/FixedLengthRequest">typeNS:_CSEaiHeader</root-type-qname>
        <qname-scope>complexType</qname-scope>
        <variable-mapping>
            <java-variable-name>applicationId</java-variable-name>
            <xml-element-name>applicationId</xml-element-name>
        </variable-mapping>
        <variable-mapping>
            <java-variable-name>transactionId</java-variable-name>
            <xml-element-name>transactionId</xml-element-name>
        </variable-mapping>
        <variable-mapping>
            <java-variable-name>messageId</java-variable-name>
            <xml-element-name>messageId</xml-element-name>
        </variable-mapping>
        <variable-mapping>
            <java-variable-name>messageHistory</java-variable-name>
            <xml-element-name>messageHistory</xml-element-name>
        </variable-mapping>
        <variable-mapping>
            <java-variable-name>tracingId</java-variable-name>
            <xml-element-name>tracingId</xml-element-name>
        </variable-mapping>
        <variable-mapping>
            <java-variable-name>timeStamp</java-variable-name>
            <xml-element-name>timeStamp</xml-element-name>
        </variable-mapping>
        <variable-mapping>
            <java-variable-name>instanceId</java-variable-name>
            <xml-element-name>instanceId</xml-element-name>
        </variable-mapping>
        <variable-mapping>
            <java-variable-name>timeToLive</java-variable-name>
            <xml-element-name>timeToLive</xml-element-name>
        </variable-mapping>
        <variable-mapping>
            <java-variable-name>payloadVersion</java-variable-name>
            <xml-element-name>payloadVersion</xml-element-name>
        </variable-mapping>
    </java-xml-type-mapping>
    <java-xml-type-mapping>
        <java-type>com.reuters.ns._2007._09._01.gcap.eai.cs.acm.accountcontactpublish._CSAccount</java-type>
        <root-type-qname xmlns:typeNS="http://www.reuters.com/ns/2007/09/01/GCAP/EAI/CS/ACM/AccountContactPublish">typeNS:_CSAccount</root-type-qname>
        <qname-scope>complexType</qname-scope>
        <variable-mapping>
            <java-variable-name>subscriberNumber</java-variable-name>
            <xml-element-name>subscriberNumber</xml-element-name>
        </variable-mapping>
        <variable-mapping>
            <java-variable-name>subscriberName</java-variable-name>
            <xml-element-name>subscriberName</xml-element-name>
        </variable-mapping>
        <variable-mapping>
            <java-variable-name>irasRef</java-variable-name>
            <xml-element-name>irasRef</xml-element-name>
        </variable-mapping>
        <variable-mapping>
            <java-variable-name>subscriberType</java-variable-name>
            <xml-element-name>subscriberType</xml-element-name>
        </variable-mapping>
        <variable-mapping>
            <java-variable-name>subscriberRelation</java-variable-name>
            <xml-element-name>subscriberRelation</xml-element-name>
        </variable-mapping>
        <variable-mapping>
            <java-variable-name>ifaceInd</java-variable-name>
            <xml-element-name>ifaceInd</xml-element-name>
        </variable-mapping>
        <variable-mapping>
            <java-variable-name>billingFrequency</java-variable-name>
            <xml-element-name>billingFrequency</xml-element-name>
        </variable-mapping>
        <variable-mapping>
            <java-variable-name>businessCategory</java-variable-name>
            <xml-element-name>businessCategory</xml-element-name>
        </variable-mapping>
        <variable-mapping>
            <java-variable-name>businessArea</java-variable-name>
            <xml-element-name>businessArea</xml-element-name>
        </variable-mapping>
        <variable-mapping>
            <java-variable-name>subFG1</java-variable-name>
            <xml-element-name>subFG1</xml-element-name>
        </variable-mapping>
        <variable-mapping>
            <java-variable-name>subFG2</java-variable-name>
            <xml-element-name>subFG2</xml-element-name>
        </variable-mapping>
        <variable-mapping>
            <java-variable-name>subscriberTaxCode</java-variable-name>
            <xml-element-name>subscriberTaxCode</xml-element-name>
        </variable-mapping>
        <variable-mapping>
            <java-variable-name>subscriberPayTerms</java-variable-name>
            <xml-element-name>subscriberPayTerms</xml-element-name>
        </variable-mapping>
        <variable-mapping>
            <java-variable-name>MCCCode</java-variable-name>
            <xml-element-name>MCCCode</xml-element-name>
        </variable-mapping>
        <variable-mapping>
            <java-variable-name>subMulticSubno</java-variable-name>
            <xml-element-name>subMulticSubno</xml-element-name>
        </variable-mapping>
        <variable-mapping>
            <java-variable-name>shortName</java-variable-name>
            <xml-element-name>shortName</xml-element-name>
        </variable-mapping>
        <variable-mapping>
            <java-variable-name>cityCode</java-variable-name>
            <xml-element-name>cityCode</xml-element-name>
        </variable-mapping>
        <variable-mapping>
            <java-variable-name>subUserShortName</java-variable-name>
            <xml-element-name>subUserShortName</xml-element-name>
        </variable-mapping>
        <variable-mapping>
            <java-variable-name>dirName</java-variable-name>
            <xml-element-name>dirName</xml-element-name>
        </variable-mapping>
        <variable-mapping>
            <java-variable-name>enterpriseCode</java-variable-name>
            <xml-element-name>enterpriseCode</xml-element-name>
        </variable-mapping>
        <variable-mapping>
            <java-variable-name>VATNumber</java-variable-name>
            <xml-element-name>VATNumber</xml-element-name>
        </variable-mapping>
        <variable-mapping>
            <java-variable-name>billingSubscriberNumber</java-variable-name>
            <xml-element-name>billingSubscriberNumber</xml-element-name>
        </variable-mapping>
        <variable-mapping>
            <java-variable-name>status</java-variable-name>
            <xml-element-name>status</xml-element-name>
        </variable-mapping>
        <variable-mapping>
            <java-variable-name>perClient</java-variable-name>
            <xml-element-name>perClient</xml-element-name>
        </variable-mapping>
        <variable-mapping>
            <java-variable-name>billingSuspensionRequired</java-variable-name>
            <xml-element-name>billingSuspensionRequired</xml-element-name>
        </variable-mapping>
        <variable-mapping>
            <java-variable-name>invoicingSummary</java-variable-name>
            <xml-element-name>invoicingSummary</xml-element-name>
        </variable-mapping>
        <variable-mapping>
            <java-variable-name>CRHoldRequired</java-variable-name>
            <xml-element-name>CRHoldRequired</xml-element-name>
        </variable-mapping>
        <variable-mapping>
            <java-variable-name>directDebitRequired</java-variable-name>
            <xml-element-name>directDebitRequired</xml-element-name>
        </variable-mapping>
        <variable-mapping>
            <java-variable-name>exPostel</java-variable-name>
            <xml-element-name>exPostel</xml-element-name>
        </variable-mapping>
        <variable-mapping>
            <java-variable-name>taxOffice</java-variable-name>
            <xml-element-name>taxOffice</xml-element-name>
        </variable-mapping>
        <variable-mapping>
            <java-variable-name>RIOIndicator</java-variable-name>
            <xml-element-name>RIOIndicator</xml-element-name>
        </variable-mapping>
        <variable-mapping>
            <java-variable-name>contractType</java-variable-name>
            <xml-element-name>contractType</xml-element-name>
        </variable-mapping>
        <variable-mapping>
            <java-variable-name>messageId</java-variable-name>
            <xml-element-name>messageId</xml-element-name>
        </variable-mapping>
		 <variable-mapping>
            <java-variable-name>globalSubNum</java-variable-name>
            <xml-element-name>globalSubNum</xml-element-name>
        </variable-mapping>		
    </java-xml-type-mapping>
    <java-xml-type-mapping>
        <java-type>com.reuters.ns._2007._09._01.gcap.eai.cs.acm.accountcontactpublish._CSCompassMessageHeader</java-type>
        <root-type-qname xmlns:typeNS="http://www.reuters.com/ns/2007/09/01/GCAP/EAI/CS/ACM/AccountContactPublish">typeNS:_CSCompassMessageHeader</root-type-qname>
        <qname-scope>complexType</qname-scope>
        <variable-mapping>
            <java-variable-name>messageId</java-variable-name>
            <xml-element-name>messageId</xml-element-name>
        </variable-mapping>
        <variable-mapping>
            <java-variable-name>transactionId</java-variable-name>
            <xml-element-name>transactionId</xml-element-name>
        </variable-mapping>
        <variable-mapping>
            <java-variable-name>messageHistory</java-variable-name>
            <xml-element-name>messageHistory</xml-element-name>
        </variable-mapping>
        <variable-mapping>
            <java-variable-name>tracingId</java-variable-name>
            <xml-element-name>tracingId</xml-element-name>
        </variable-mapping>
        <variable-mapping>
            <java-variable-name>messageCode</java-variable-name>
            <xml-element-name>messageCode</xml-element-name>
        </variable-mapping>
        <variable-mapping>
            <java-variable-name>version</java-variable-name>
            <xml-element-name>version</xml-element-name>
        </variable-mapping>
        <variable-mapping>
            <java-variable-name>timeStamp</java-variable-name>
            <xml-element-name>timeStamp</xml-element-name>
        </variable-mapping>
        <variable-mapping>
            <java-variable-name>userId</java-variable-name>
            <xml-element-name>userId</xml-element-name>
        </variable-mapping>
        <variable-mapping>
            <java-variable-name>objectSystem</java-variable-name>
            <xml-element-name>objectSystem</xml-element-name>
        </variable-mapping>
    </java-xml-type-mapping>
    <java-xml-type-mapping>
        <java-type>com.reuters.ns._2007._09._01.gcap.eai.cs.fixedlengthrequest.FixedLengthRequest</java-type>
        <root-type-qname xmlns:typeNS="http://www.reuters.com/ns/2007/09/01/GCAP/EAI/CS/FixedLengthRequest">typeNS:FixedLengthRequest</root-type-qname>
        <qname-scope>complexType</qname-scope>
        <variable-mapping>
            <java-variable-name>eaiHeader</java-variable-name>
            <xml-element-name>eaiHeader</xml-element-name>
        </variable-mapping>
        <variable-mapping>
            <java-variable-name>basicResponse</java-variable-name>
            <xml-element-name>basicResponse</xml-element-name>
        </variable-mapping>
        <variable-mapping>
            <java-variable-name>logicalCountry</java-variable-name>
            <xml-element-name>logicalCountry</xml-element-name>
        </variable-mapping>
        <variable-mapping>
            <java-variable-name>message</java-variable-name>
            <xml-element-name>message</xml-element-name>
        </variable-mapping>
    </java-xml-type-mapping>
    <java-xml-type-mapping>
        <java-type>com.reuters.ns._2007._09._01.gcap.eai.cs.acm.accountcontactpublish._CSInstallationAddress</java-type>
        <root-type-qname xmlns:typeNS="http://www.reuters.com/ns/2007/09/01/GCAP/EAI/CS/ACM/AccountContactPublish">typeNS:_CSInstallationAddress</root-type-qname>
        <qname-scope>complexType</qname-scope>
        <variable-mapping>
            <java-variable-name>subAccount</java-variable-name>
            <xml-element-name>subAccount</xml-element-name>
        </variable-mapping>
        <variable-mapping>
            <java-variable-name>name1</java-variable-name>
            <xml-element-name>name1</xml-element-name>
        </variable-mapping>
        <variable-mapping>
            <java-variable-name>name2</java-variable-name>
            <xml-element-name>name2</xml-element-name>
        </variable-mapping>
        <variable-mapping>
            <java-variable-name>building</java-variable-name>
            <xml-element-name>building</xml-element-name>
        </variable-mapping>
        <variable-mapping>
            <java-variable-name>street</java-variable-name>
            <xml-element-name>street</xml-element-name>
        </variable-mapping>
        <variable-mapping>
            <java-variable-name>city</java-variable-name>
            <xml-element-name>city</xml-element-name>
        </variable-mapping>
        <variable-mapping>
            <java-variable-name>state</java-variable-name>
            <xml-element-name>state</xml-element-name>
        </variable-mapping>
        <variable-mapping>
            <java-variable-name>country</java-variable-name>
            <xml-element-name>country</xml-element-name>
        </variable-mapping>
        <variable-mapping>
            <java-variable-name>zipCode</java-variable-name>
            <xml-element-name>zipCode</xml-element-name>
        </variable-mapping>
        <variable-mapping>
            <java-variable-name>geoCode</java-variable-name>
            <xml-element-name>GeoCode</xml-element-name>
        </variable-mapping>
        <variable-mapping>
            <java-variable-name>status</java-variable-name>
            <xml-element-name>status</xml-element-name>
        </variable-mapping>
        <variable-mapping>
            <java-variable-name>perClient</java-variable-name>
            <xml-element-name>perClient</xml-element-name>
        </variable-mapping>
        <variable-mapping>
            <java-variable-name>billingSuspensionRequired</java-variable-name>
            <xml-element-name>billingSuspensionRequired</xml-element-name>
        </variable-mapping>
        <variable-mapping>
            <java-variable-name>accountNotes</java-variable-name>
            <xml-element-name>accountNotes</xml-element-name>
        </variable-mapping>
        <variable-mapping>
            <java-variable-name>accountDescription</java-variable-name>
            <xml-element-name>accountDescription</xml-element-name>
        </variable-mapping>
        <variable-mapping>
            <java-variable-name>customerReference</java-variable-name>
            <xml-element-name>customerReference</xml-element-name>
        </variable-mapping>
        <variable-mapping>
            <java-variable-name>RIPurchaseOrder</java-variable-name>
            <xml-element-name>RIPurchaseOrder</xml-element-name>
        </variable-mapping>
        <variable-mapping>
            <java-variable-name>ERPurchaseOrder</java-variable-name>
            <xml-element-name>ERPurchaseOrder</xml-element-name>
        </variable-mapping>
    </java-xml-type-mapping>
    <java-xml-type-mapping>
        <java-type>com.reuters.ns._2007._09._01.gcap.eai.cs.acm.accountcontactpublish._CSBillingAddress</java-type>
        <root-type-qname xmlns:typeNS="http://www.reuters.com/ns/2007/09/01/GCAP/EAI/CS/ACM/AccountContactPublish">typeNS:_CSBillingAddress</root-type-qname>
        <qname-scope>complexType</qname-scope>
        <variable-mapping>
            <java-variable-name>subAccount</java-variable-name>
            <xml-element-name>subAccount</xml-element-name>
        </variable-mapping>
        <variable-mapping>
            <java-variable-name>name1</java-variable-name>
            <xml-element-name>name1</xml-element-name>
        </variable-mapping>
        <variable-mapping>
            <java-variable-name>name2</java-variable-name>
            <xml-element-name>name2</xml-element-name>
        </variable-mapping>
        <variable-mapping>
            <java-variable-name>building</java-variable-name>
            <xml-element-name>building</xml-element-name>
        </variable-mapping>
        <variable-mapping>
            <java-variable-name>street</java-variable-name>
            <xml-element-name>street</xml-element-name>
        </variable-mapping>
        <variable-mapping>
            <java-variable-name>city</java-variable-name>
            <xml-element-name>city</xml-element-name>
        </variable-mapping>
        <variable-mapping>
            <java-variable-name>state</java-variable-name>
            <xml-element-name>state</xml-element-name>
        </variable-mapping>
        <variable-mapping>
            <java-variable-name>country</java-variable-name>
            <xml-element-name>country</xml-element-name>
        </variable-mapping>
        <variable-mapping>
            <java-variable-name>zipCode</java-variable-name>
            <xml-element-name>zipCode</xml-element-name>
        </variable-mapping>
        <variable-mapping>
            <java-variable-name>geoCode</java-variable-name>
            <xml-element-name>GeoCode</xml-element-name>
        </variable-mapping>
        <variable-mapping>
            <java-variable-name>status</java-variable-name>
            <xml-element-name>status</xml-element-name>
        </variable-mapping>
        <variable-mapping>
            <java-variable-name>perClient</java-variable-name>
            <xml-element-name>perClient</xml-element-name>
        </variable-mapping>
        <variable-mapping>
            <java-variable-name>billingSuspensionRequired</java-variable-name>
            <xml-element-name>billingSuspensionRequired</xml-element-name>
        </variable-mapping>
        <variable-mapping>
            <java-variable-name>accountNotes</java-variable-name>
            <xml-element-name>accountNotes</xml-element-name>
        </variable-mapping>
        <variable-mapping>
            <java-variable-name>accountDescription</java-variable-name>
            <xml-element-name>accountDescription</xml-element-name>
        </variable-mapping>
        <variable-mapping>
            <java-variable-name>customerReference</java-variable-name>
            <xml-element-name>customerReference</xml-element-name>
        </variable-mapping>
        <variable-mapping>
            <java-variable-name>RIPurchaseOrder</java-variable-name>
            <xml-element-name>RIPurchaseOrder</xml-element-name>
        </variable-mapping>
        <variable-mapping>
            <java-variable-name>ERPurchaseOrder</java-variable-name>
            <xml-element-name>ERPurchaseOrder</xml-element-name>
        </variable-mapping>
    </java-xml-type-mapping>
    <java-xml-type-mapping>
        <java-type>com.reuters.ns._2007._09._01.gcap.eai.cs.acm.accountcontactpublish._CSAccountContactPublish</java-type>
        <root-type-qname xmlns:typeNS="http://www.reuters.com/ns/2007/09/01/GCAP/EAI/CS/ACM/AccountContactPublish">typeNS:_CSAccountContactPublish</root-type-qname>
        <qname-scope>complexType</qname-scope>
        <variable-mapping>
            <java-variable-name>eaiHeader</java-variable-name>
            <xml-element-name>eaiHeader</xml-element-name>
        </variable-mapping>
        <variable-mapping>
            <java-variable-name>messageHeader</java-variable-name>
            <xml-element-name>messageHeader</xml-element-name>
        </variable-mapping>
        <variable-mapping>
            <java-variable-name>country</java-variable-name>
            <xml-element-name>country</xml-element-name>
        </variable-mapping>
        <variable-mapping>
            <java-variable-name>accountId</java-variable-name>
            <xml-element-name>AccountId</xml-element-name>
        </variable-mapping>
        <variable-mapping>
            <java-variable-name>account</java-variable-name>
            <xml-element-name>account</xml-element-name>
        </variable-mapping>
        <variable-mapping>
            <java-variable-name>installAddress</java-variable-name>
            <xml-element-name>installAddress</xml-element-name>
        </variable-mapping>
        <variable-mapping>
            <java-variable-name>billingAddress</java-variable-name>
            <xml-element-name>billingAddress</xml-element-name>
        </variable-mapping>
        <variable-mapping>
            <java-variable-name>contact</java-variable-name>
            <xml-element-name>contact</xml-element-name>
        </variable-mapping>
    </java-xml-type-mapping>
    <java-xml-type-mapping>
        <java-type>com.reuters.ns._2007._09._01.gcap.eai.cs.acm.accountcontactpublish._CSEaiHeader</java-type>
        <root-type-qname xmlns:typeNS="http://www.reuters.com/ns/2007/09/01/GCAP/EAI/CS/ACM/AccountContactPublish">typeNS:_CSEaiHeader</root-type-qname>
        <qname-scope>complexType</qname-scope>
        <variable-mapping>
            <java-variable-name>applicationId</java-variable-name>
            <xml-element-name>applicationId</xml-element-name>
        </variable-mapping>
        <variable-mapping>
            <java-variable-name>transactionId</java-variable-name>
            <xml-element-name>transactionId</xml-element-name>
        </variable-mapping>
        <variable-mapping>
            <java-variable-name>messageId</java-variable-name>
            <xml-element-name>messageId</xml-element-name>
        </variable-mapping>
        <variable-mapping>
            <java-variable-name>messageHistory</java-variable-name>
            <xml-element-name>messageHistory</xml-element-name>
        </variable-mapping>
        <variable-mapping>
            <java-variable-name>tracingId</java-variable-name>
            <xml-element-name>tracingId</xml-element-name>
        </variable-mapping>
        <variable-mapping>
            <java-variable-name>timeStamp</java-variable-name>
            <xml-element-name>timeStamp</xml-element-name>
        </variable-mapping>
        <variable-mapping>
            <java-variable-name>instanceId</java-variable-name>
            <xml-element-name>instanceId</xml-element-name>
        </variable-mapping>
        <variable-mapping>
            <java-variable-name>timeToLive</java-variable-name>
            <xml-element-name>timeToLive</xml-element-name>
        </variable-mapping>
        <variable-mapping>
            <java-variable-name>payloadVersion</java-variable-name>
            <xml-element-name>payloadVersion</xml-element-name>
        </variable-mapping>
    </java-xml-type-mapping>
    <java-xml-type-mapping>
        <java-type>com.reuters.ns._2007._09._01.gcap.eai.cs.acm.accountcontactpublish._CSContact[]</java-type>
        <anonymous-type-qname>{http://www.reuters.com/ns/2007/09/01/GCAP/EAI/CS/ACM/AccountContactPublish}_CSAccountContactPublish&gt;contact[0,unbounded]</anonymous-type-qname>
        <qname-scope>complexType</qname-scope>
    </java-xml-type-mapping>
    <service-interface-mapping>
        <service-interface>com.reuters.eai.cs.acm.TransformAccountContactToCSFormat</service-interface>
        <wsdl-service-name xmlns:serviceNS="http://www.reuters.com/ns/2007/09/01/GCAP/CS/ACM/AccountContactRequestFormatter">serviceNS:TransformAccountContactToCSFormat</wsdl-service-name>
        <port-mapping>
            <port-name>AccountContactRequest</port-name>
            <java-port-name>AccountContactRequest</java-port-name>
        </port-mapping>
    </service-interface-mapping>
    <service-endpoint-interface-mapping>
        <service-endpoint-interface>com.reuters.eai.cs.acm.TransformAccountContactRequest</service-endpoint-interface>
        <wsdl-port-type xmlns:portTypeNS="http://www.reuters.com/ns/2007/09/01/GCAP/CS/ACM/AccountContactRequestFormatter">portTypeNS:TransformAccountContactRequest</wsdl-port-type>
        <wsdl-binding xmlns:bindingNS="http://www.reuters.com/ns/2007/09/01/GCAP/CS/ACM/AccountContactRequestFormatter">bindingNS:TransformAccountContactRequestSOAP</wsdl-binding>
        <service-endpoint-method-mapping>
            <java-method-name>transform</java-method-name>
            <wsdl-operation>transform</wsdl-operation>
            <method-param-parts-mapping>
                <param-position>0</param-position>
                <param-type>com.reuters.ns._2007._09._01.gcap.eai.cs.acm.accountcontactpublish._CSAccountContactPublish</param-type>
                <wsdl-message-mapping>
                    <wsdl-message xmlns:wsdlMsgNS="http://www.reuters.com/ns/2007/09/01/GCAP/CS/ACM/AccountContactRequestFormatter">wsdlMsgNS:AccountContactRequest</wsdl-message>
                    <wsdl-message-part-name>parameter</wsdl-message-part-name>
                    <parameter-mode>IN</parameter-mode>
                </wsdl-message-mapping>
            </method-param-parts-mapping>
            <wsdl-return-value-mapping>
                <method-return-value>com.reuters.ns._2007._09._01.gcap.eai.cs.fixedlengthrequest.FixedLengthRequest</method-return-value>
                <wsdl-message xmlns:wsdlMsgNS="http://www.reuters.com/ns/2007/09/01/GCAP/CS/ACM/AccountContactRequestFormatter">wsdlMsgNS:AccountContactResponse</wsdl-message>
                <wsdl-message-part-name>parameter</wsdl-message-part-name>
            </wsdl-return-value-mapping>
        </service-endpoint-method-mapping>
    </service-endpoint-interface-mapping>
</java-wsdl-mapping>

