<?xml version='1.0' encoding='UTF-8'?>
<weblogic-webservices xmlns="http://www.bea.com/ns/weblogic/90"><webservice-description>
   <webservice-description-name>TransformOrderRequest</webservice-description-name>
    <port-component>
      <port-component-name>OrderRequest</port-component-name>
      <service-endpoint-address>
        <webservice-contextpath>/TransformOrderRequest</webservice-contextpath>
        <webservice-serviceuri>/TransformOrderRequest</webservice-serviceuri>
      </service-endpoint-address>
    </port-component>
  </webservice-description>
</weblogic-webservices>